{
  "annotations": {
    "list": [
      {
        "builtIn": 1,
        "datasource": {
          "type": "grafana",
          "uid": "-- Grafana --"
        },
        "enable": true,
        "hide": true,
        "iconColor": "rgba(0, 211, 255, 1)",
        "name": "Annotations & Alerts",
        "type": "dashboard"
      }
    ]
  },
  "editable": true,
  "fiscalYearStartMonth": 0,
  "graphTooltip": 0,
  "id": 2,
  "links": [],
  "panels": [
    {
      "datasource": {
        "type": "prometheus",
        "uid": "adexcj24pfxfkf"
      },
      "fieldConfig": {
        "defaults": {
          "color": {
            "mode": "thresholds"
          },
          "decimals": 2,
          "mappings": [],
          "max": 100,
          "min": 1,
          "thresholds": {
            "mode": "absolute",
            "steps": [
              {
                "color": "dark-green",
                "value": null
              },
              {
                "color": "dark-yellow",
                "value": 85
              },
              {
                "color": "dark-red",
                "value": 95
              }
            ]
          },
          "unit": "percent"
        },
        "overrides": []
      },
      "gridPos": {
        "h": 12,
        "w": 12,
        "x": 0,
        "y": 0
      },
      "id": 1,
      "options": {
        "minVizHeight": 75,
        "minVizWidth": 75,
        "orientation": "auto",
        "reduceOptions": {
          "calcs": [
            "lastNotNull"
          ],
          "fields": "",
          "values": false
        },
        "showThresholdLabels": false,
        "showThresholdMarkers": true,
        "sizing": "auto"
      },
      "pluginVersion": "10.4.0",
      "targets": [
        {
          "datasource": {
            "type": "prometheus",
            "uid": "adexcj24pfxfkf"
          },
          "disableTextWrap": false,
          "editorMode": "builder",
          "exemplar": false,
          "expr": "overall_cpu_usage",
          "fullMetaSearch": false,
          "includeNullMetadata": true,
          "instant": true,
          "legendFormat": "__auto",
          "range": false,
          "refId": "A",
          "useBackend": false
        }
      ],
      "title": "Overall CPU Usage",
      "transparent": true,
      "type": "gauge"
    },
    {
      "datasource": {
        "type": "prometheus",
        "uid": "adexcj24pfxfkf"
      },
      "fieldConfig": {
        "defaults": {
          "color": {
            "mode": "palette-classic"
          },
          "custom": {
            "axisBorderShow": false,
            "axisCenteredZero": false,
            "axisColorMode": "text",
            "axisLabel": "",
            "axisPlacement": "auto",
            "barAlignment": 0,
            "drawStyle": "line",
            "fillOpacity": 0,
            "gradientMode": "none",
            "hideFrom": {
              "legend": false,
              "tooltip": false,
              "viz": false
            },
            "insertNulls": false,
            "lineInterpolation": "linear",
            "lineWidth": 1,
            "pointSize": 5,
            "scaleDistribution": {
              "type": "linear"
            },
            "showPoints": "auto",
            "spanNulls": false,
            "stacking": {
              "group": "A",
              "mode": "none"
            },
            "thresholdsStyle": {
              "mode": "off"
            }
          },
          "mappings": [],
          "thresholds": {
            "mode": "absolute",
            "steps": [
              {
                "color": "green",
                "value": null
              },
              {
                "color": "red",
                "value": 80
              }
            ]
          }
        },
        "overrides": []
      },
      "gridPos": {
        "h": 12,
        "w": 12,
        "x": 12,
        "y": 0
      },
      "id": 7,
      "options": {
        "legend": {
          "calcs": [
            "lastNotNull"
          ],
          "displayMode": "list",
          "placement": "bottom",
          "showLegend": true
        },
        "tooltip": {
          "mode": "single",
          "sort": "none"
        }
      },
      "targets": [
        {
          "datasource": {
            "type": "prometheus",
            "uid": "adexcj24pfxfkf"
          },
          "disableTextWrap": false,
          "editorMode": "builder",
          "expr": "overall_cpu_usage",
          "fullMetaSearch": false,
          "includeNullMetadata": true,
          "instant": false,
          "legendFormat": "__auto",
          "range": true,
          "refId": "A",
          "useBackend": false
        }
      ],
      "title": "Usage over time",
      "transparent": true,
      "type": "timeseries"
    },
    {
      "collapsed": false,
      "gridPos": {
        "h": 1,
        "w": 24,
        "x": 0,
        "y": 12
      },
      "id": 2,
      "panels": [],
      "title": "per-core usage",
      "type": "row"
    },
    {
      "datasource": {
        "type": "prometheus",
        "uid": "adexcj24pfxfkf"
      },
      "fieldConfig": {
        "defaults": {
          "color": {
            "mode": "thresholds"
          },
          "decimals": 2,
          "mappings": [],
          "max": 100,
          "min": 1,
          "thresholds": {
            "mode": "percentage",
            "steps": [
              {
                "color": "dark-green",
                "value": null
              },
              {
                "color": "dark-yellow",
                "value": 80
              },
              {
                "color": "dark-red",
                "value": 95
              }
            ]
          },
          "unit": "percent"
        },
        "overrides": []
      },
      "gridPos": {
        "h": 7,
        "w": 6,
        "x": 0,
        "y": 13
      },
      "id": 3,
      "maxPerRow": 6,
      "options": {
        "minVizHeight": 75,
        "minVizWidth": 75,
        "orientation": "auto",
        "reduceOptions": {
          "calcs": [
            "lastNotNull"
          ],
          "fields": "",
          "values": false
        },
        "showThresholdLabels": false,
        "showThresholdMarkers": true,
        "sizing": "auto"
      },
      "pluginVersion": "10.4.0",
      "repeat": "cpu_core",
      "repeatDirection": "h",
      "targets": [
        {
          "datasource": {
            "type": "prometheus",
            "uid": "adexcj24pfxfkf"
          },
          "disableTextWrap": false,
          "editorMode": "builder",
          "expr": "$cpu_core",
          "fullMetaSearch": false,
          "includeNullMetadata": true,
          "instant": false,
          "legendFormat": "__auto",
          "range": true,
          "refId": "A",
          "useBackend": false
        }
      ],
      "title": "$cpu_core",
      "transparent": true,
      "type": "gauge"
    }
  ],
  "refresh": "",
  "schemaVersion": 39,
  "tags": [],
  "templating": {
    "list": [
      {
        "allValue": "",
        "current": {
          "selected": true,
          "text": [
            "cpu_0_usage",
            "cpu_1_usage",
            "cpu_2_usage",
            "cpu_3_usage"
          ],
          "value": [
            "cpu_0_usage",
            "cpu_1_usage",
            "cpu_2_usage",
            "cpu_3_usage"
          ]
        },
        "datasource": {
          "type": "prometheus",
          "uid": "adexcj24pfxfkf"
        },
        "definition": "metrics((cpu_)(.)(_usage))",
        "hide": 0,
        "includeAll": true,
        "multi": true,
        "name": "cpu_core",
        "options": [],
        "query": {
          "qryType": 2,
          "query": "metrics((cpu_)(.)(_usage))",
          "refId": "PrometheusVariableQueryEditor-VariableQuery"
        },
        "refresh": 1,
        "regex": "",
        "skipUrlSync": false,
        "sort": 0,
        "type": "query"
      }
    ]
  },
  "time": {
    "from": "now-5m",
    "to": "now"
  },
  "timepicker": {},
  "timezone": "browser",
  "title": "system-monitor",
  "uid": "admo2uf9cg8owe",
  "version": 16,
  "weekStart": ""
}